odoo/addons/hr_contract_document/README.rst
odoo/addons/hr_contract_document/__init__.py
odoo/addons/hr_contract_document/__manifest__.py
odoo/addons/hr_contract_document/i18n/es.po
odoo/addons/hr_contract_document/i18n/hr_contract_document.pot
odoo/addons/hr_contract_document/i18n/it.po
odoo/addons/hr_contract_document/models/__init__.py
odoo/addons/hr_contract_document/models/hr_contract.py
odoo/addons/hr_contract_document/readme/CONTRIBUTORS.rst
odoo/addons/hr_contract_document/readme/DESCRIPTION.rst
odoo/addons/hr_contract_document/static/description/icon.png
odoo/addons/hr_contract_document/static/description/index.html
odoo/addons/hr_contract_document/tests/__init__.py
odoo/addons/hr_contract_document/tests/test_hr_contract_document.py
odoo/addons/hr_contract_document/views/hr_contract.xml
odoo/addons/hr_contract_document/views/ir_attachment.xml
odoo13_addon_hr_contract_document-13.0.1.0.1.dev9.dist-info/METADATA
odoo13_addon_hr_contract_document-13.0.1.0.1.dev9.dist-info/WHEEL
odoo13_addon_hr_contract_document-13.0.1.0.1.dev9.dist-info/top_level.txt
odoo13_addon_hr_contract_document-13.0.1.0.1.dev9.dist-info/RECORD
